<PAMDataset>
  <PAMRasterBand band="1">
    <Histograms>
      <HistItem>
        <HistMin>-37.94384765625</HistMin>
        <HistMax>41.269805908203</HistMax>
        <BucketCount>256</BucketCount>
        <IncludeOutOfRange>1</IncludeOutOfRange>
        <Approximate>0</Approximate>
        <HistCounts>1|0|0|0|0|0|0|0|0|0|0|0|0|0|1|0|2|0|0|0|0|1|0|1|0|0|1|0|0|4|3|2|1|0|1|2|4|1|1|0|2|4|2|5|6|4|5|8|3|12|6|8|9|10|9|3|11|12|19|18|12|18|26|26|23|39|38|27|39|46|52|58|76|83|84|105|112|103|127|165|188|188|229|260|279|338|380|400|482|563|627|738|857|962|1141|1296|1553|1706|2048|2406|2783|3379|3986|4665|5601|6822|8140|9868|12098|14669|17848|22070|27206|33237|41011|51198|63562|79409|98923|125607|159523|204771|212059|162660|125536|100191|79488|64221|51890|42424|34429|27971|22938|19207|15692|13016|10999|9067|7613|6312|5472|4468|3801|3271|2706|2404|2092|1828|1521|1314|1137|977|851|729|614|567|549|440|423|346|309|285|251|223|145|158|142|137|118|115|102|80|83|71|57|69|48|48|40|41|39|19|36|17|30|21|12|20|10|20|12|13|11|11|6|6|10|4|3|8|2|3|3|0|4|3|3|3|0|2|3|3|2|0|1|1|0|0|1|1|1|1|1|1|1|0|0|0|1|0|1|0|0|0|0|0|2|0|0|0|0|0|1|0|0|0|0|0|1|0|0|0|0|0|0|1</HistCounts>
      </HistItem>
    </Histograms>
    <Metadata>
      <MDI key="STATISTICS_COVARIANCES">5.461326182882667</MDI>
      <MDI key="STATISTICS_MAXIMUM">41.269805908203</MDI>
      <MDI key="STATISTICS_MEAN">-0.00027536080293915</MDI>
      <MDI key="STATISTICS_MINIMUM">-37.94384765625</MDI>
      <MDI key="STATISTICS_SKIPFACTORX">1</MDI>
      <MDI key="STATISTICS_SKIPFACTORY">1</MDI>
      <MDI key="STATISTICS_STDDEV">2.3369480488198</MDI>
    </Metadata>
  </PAMRasterBand>
</PAMDataset>
